rte/__init__.py
rte/medium.py
rte/process.py
rte/sources.py
rte/steps.py
rte/utils.py
rte/viewer.py
RTE-0.1.0.dist-info/METADATA
RTE-0.1.0.dist-info/WHEEL
RTE-0.1.0.dist-info/top_level.txt
RTE-0.1.0.dist-info/RECORD
