Metadata-Version: 2.1
Name: RTE
Version: 0.1.0
Summary: Package for calculating the photon flux using the Radiative Transfer Equation
Project-URL: Homepage, https://github.com/RTESolution/rte
Project-URL: Issues, https://github.com/RTESolution/rte/issues
Classifier: Programming Language :: Python :: 3
Classifier: License :: OSI Approved :: MIT License
Classifier: Operating System :: OS Independent
Requires-Python: >=3.9
Requires-Dist: vegas_params~=0.1
Requires-Dist: tqdm
Requires-Dist: loguru
Provides-Extra: gui
Requires-Dist: PyOpenGL~=3.0; extra == "gui"
Requires-Dist: PySide6~=6.7; extra == "gui"
Requires-Dist: pyqtgraph~=0.13; extra == "gui"
Provides-Extra: test
Requires-Dist: pytest>=8; extra == "test"
